chuk_ai_planner/__init__.py
chuk_ai_planner/jobs.py
chuk_ai_planner/processor.py
chuk_ai_planner/agents/__init__.py
chuk_ai_planner/agents/graph_plan_agent.py
chuk_ai_planner/agents/plan_agent.py
chuk_ai_planner/core/__init__.py
chuk_ai_planner/core/graph/__init__.py
chuk_ai_planner/core/graph/node_manager.py
chuk_ai_planner/core/graph/types.py
chuk_ai_planner/core/graph/edges/__init__.py
chuk_ai_planner/core/graph/edges/base.py
chuk_ai_planner/core/graph/edges/hierarchy.py
chuk_ai_planner/core/graph/edges/ordering.py
chuk_ai_planner/core/graph/edges/planning.py
chuk_ai_planner/core/graph/edges/routing.py
chuk_ai_planner/core/graph/edges/workflow.py
chuk_ai_planner/core/graph/nodes/__init__.py
chuk_ai_planner/core/graph/nodes/artifact.py
chuk_ai_planner/core/graph/nodes/base.py
chuk_ai_planner/core/graph/nodes/execution.py
chuk_ai_planner/core/graph/nodes/job.py
chuk_ai_planner/core/graph/nodes/plan.py
chuk_ai_planner/core/graph/nodes/session.py
chuk_ai_planner/core/graph/nodes/workflow.py
chuk_ai_planner/core/planner/__init__.py
chuk_ai_planner/core/planner/_ids.py
chuk_ai_planner/core/planner/_persist.py
chuk_ai_planner/core/planner/_step_tree.py
chuk_ai_planner/core/planner/plan.py
chuk_ai_planner/core/planner/plan_executor.py
chuk_ai_planner/core/planner/plan_registry.py
chuk_ai_planner/core/planner/universal_plan.py
chuk_ai_planner/core/planner/universal_plan_executor.py
chuk_ai_planner/core/routing/__init__.py
chuk_ai_planner/core/routing/executor.py
chuk_ai_planner/core/store/__init__.py
chuk_ai_planner/core/store/base.py
chuk_ai_planner/core/store/memory.py
chuk_ai_planner/execution/__init__.py
chuk_ai_planner/execution/ctp_backend.py
chuk_ai_planner/execution/interfaces.py
chuk_ai_planner/execution/models.py
chuk_ai_planner/extensions/__init__.py
chuk_ai_planner/extensions/llm/__init__.py
chuk_ai_planner/extensions/llm/nodes.py
chuk_ai_planner/extensions/llm/types.py
chuk_ai_planner/utils/__init__.py
chuk_ai_planner/utils/pretty.py
chuk_ai_planner-0.5.1.dist-info/METADATA
chuk_ai_planner-0.5.1.dist-info/WHEEL
chuk_ai_planner-0.5.1.dist-info/top_level.txt
chuk_ai_planner-0.5.1.dist-info/RECORD
