Metadata-Version: 2.4
Name: chuk-ai-planner
Version: 0.5.1
Summary: Add your description here
Requires-Python: >=3.11
Requires-Dist: asyncio>=3.4.3
Requires-Dist: bs4>=0.0.2
Requires-Dist: chuk-session-manager>=0.1.0
Requires-Dist: chuk-tool-processor>=0.11.3
Requires-Dist: geopy>=2.4.1
Requires-Dist: lxml-html-clean>=0.4.2
Requires-Dist: openai>=1.76.2
Requires-Dist: pydantic>=2.11.4
Requires-Dist: python-dotenv>=1.1.0
Requires-Dist: readability-lxml>=0.8.1
Requires-Dist: requests>=2.32.3
Requires-Dist: uuid>=1.30
Provides-Extra: dev
Requires-Dist: matplotlib>=3.10.3; extra == "dev"
Requires-Dist: mypy>=1.15.0; extra == "dev"
Requires-Dist: networkx>=3.5; extra == "dev"
Requires-Dist: pytest>=8.0.0; extra == "dev"
Requires-Dist: pytest-asyncio>=1.0.0; extra == "dev"
Requires-Dist: pytest-cov>=6.0.0; extra == "dev"
Requires-Dist: pytest-watch>=4.2.0; extra == "dev"
Requires-Dist: ruff>=0.14.0; extra == "dev"
